build/lib/build/lib/build/lib/build/lib/build/lib/musicron/__init__.py
build/lib/build/lib/build/lib/build/lib/build/lib/musicron/__main__.py
build/lib/build/lib/build/lib/build/lib/build/lib/musicron/core/config/__init__.py
build/lib/build/lib/build/lib/build/lib/build/lib/musicron/core/plugin/__init__.py
build/lib/build/lib/build/lib/build/lib/build/lib/musicron/core/thread/__init__.py
build/lib/build/lib/build/lib/build/lib/build/lib/musicron/core/timedate/__init__.py
build/lib/build/lib/build/lib/build/lib/build/lib/musicron/plugins/__init__.py
build/lib/build/lib/build/lib/build/lib/musicron/__init__.py
build/lib/build/lib/build/lib/build/lib/musicron/__main__.py
build/lib/build/lib/build/lib/build/lib/musicron/core/config/__init__.py
build/lib/build/lib/build/lib/build/lib/musicron/core/plugin/__init__.py
build/lib/build/lib/build/lib/build/lib/musicron/core/thread/__init__.py
build/lib/build/lib/build/lib/build/lib/musicron/core/timedate/__init__.py
build/lib/build/lib/build/lib/build/lib/musicron/plugins/__init__.py
build/lib/build/lib/build/lib/build/lib/musicron/plugins/vlc/__init__.py
build/lib/build/lib/build/lib/musicron/__init__.py
build/lib/build/lib/build/lib/musicron/__main__.py
build/lib/build/lib/build/lib/musicron/core/config/__init__.py
build/lib/build/lib/build/lib/musicron/core/plugin/__init__.py
build/lib/build/lib/build/lib/musicron/core/thread/__init__.py
build/lib/build/lib/build/lib/musicron/core/timedate/__init__.py
build/lib/build/lib/build/lib/musicron/plugins/__init__.py
build/lib/build/lib/build/lib/musicron/plugins/vlc/__init__.py
build/lib/build/lib/musicron/__init__.py
build/lib/build/lib/musicron/__main__.py
build/lib/build/lib/musicron/core/config/__init__.py
build/lib/build/lib/musicron/core/plugin/__init__.py
build/lib/build/lib/musicron/core/thread/__init__.py
build/lib/build/lib/musicron/core/timedate/__init__.py
build/lib/build/lib/musicron/plugins/__init__.py
build/lib/build/lib/musicron/plugins/vlc/__init__.py
musicron-0.1.14.dist-info/LICENSE
musicron-0.1.14.dist-info/METADATA
musicron-0.1.14.dist-info/WHEEL
musicron-0.1.14.dist-info/top_level.txt
musicron-0.1.14.dist-info/RECORD
