Metadata-Version: 2.1
Name: musicron
Version: 0.1.14
Summary: A cron for music!
Home-page: https://github.com/gwfisher/musicron
Author: Wesley Fisher
Author-email: wfisher@praetor.tel
License: UNKNOWN
Platform: UNKNOWN
Classifier: Programming Language :: Python :: 3
Classifier: License :: OSI Approved :: GNU General Public License v3 (GPLv3)
Classifier: Operating System :: OS Independent
Requires-Python: >=3.7
License-File: LICENSE
Requires-Dist: dbus-python
Requires-Dist: importlib2
Requires-Dist: pathlib
Requires-Dist: psutil
Requires-Dist: python-dateutil
Requires-Dist: pyyaml
